main.py
cnpj_processor/.env.cnpj-processor
cnpj_processor/README.md
cnpj_processor/__init__.py
cnpj_processor/__version__.py
cnpj_processor/cli.py
cnpj_processor-4.2.1.dist-info/licenses/LICENSE
src/__init__.py
src/__version__.py
src/async_downloader.py
src/cache_manager.py
src/config.py
src/database.py
src/localization.py
src/localization_example.py
src/Entity/Cnae.py
src/Entity/Empresa.py
src/Entity/Estabelecimento.py
src/Entity/Lucro.py
src/Entity/Motivo.py
src/Entity/Municipio.py
src/Entity/NaturezaJuridica.py
src/Entity/Painel.py
src/Entity/QualificacaoSocio.py
src/Entity/README.md
src/Entity/Simples.py
src/Entity/Socio.py
src/Entity/TipoSituacaoCadastral.py
src/Entity/__init__.py
src/Entity/base.py
src/Entity/schemas/__init__.py
src/Entity/schemas/empresa.py
src/Entity/schemas/estabelecimento.py
src/Entity/schemas/painel.py
src/Entity/schemas/simples.py
src/Entity/schemas/socio.py
src/Entity/schemas/utils.py
src/Entity/validation/__init__.py
src/Entity/validation/batch.py
src/Entity/validation/corrections.py
src/Entity/validation/validator.py
src/process/__init__.py
src/process/base/__init__.py
src/process/base/factory.py
src/process/base/processor.py
src/process/base/queue_manager.py
src/process/base/resource_monitor.py
src/process/processors/__init__.py
src/process/processors/empresa_processor.py
src/process/processors/estabelecimento_processor.py
src/process/processors/painel_processor.py
src/process/processors/simples_processor.py
src/process/processors/socio_processor.py
src/utils/README.md
src/utils/__init__.py
src/utils/cache.py
src/utils/cli.py
src/utils/colors.py
src/utils/download_wrapper.py
src/utils/env_setup.py
src/utils/files.py
src/utils/folders.py
src/utils/global_circuit_breaker.py
src/utils/logging.py
src/utils/network.py
src/utils/nextcloud_client.py
src/utils/parallel.py
src/utils/processing_cache.py
src/utils/progress_tracker.py
src/utils/statistics.py
src/utils/time_utils.py
src/utils/utils.py
cnpj_processor-4.2.1.dist-info/METADATA
cnpj_processor-4.2.1.dist-info/WHEEL
cnpj_processor-4.2.1.dist-info/entry_points.txt
cnpj_processor-4.2.1.dist-info/top_level.txt
cnpj_processor-4.2.1.dist-info/RECORD
