Metadata-Version: 2.4
Name: cnpj-processor
Version: 4.2.1
Summary: Sistema de Processamento de Dados CNPJ da Receita Federal do Brasil
Author-email: Wesley Modanez Freitas <wesley.modanez@gmail.com>
License-Expression: MIT
Project-URL: Homepage, https://github.com/wmodanez/cnpj
Project-URL: Documentation, https://github.com/wmodanez/cnpj/blob/develop/README.md
Project-URL: Repository, https://github.com/wmodanez/cnpj
Project-URL: Issues, https://github.com/wmodanez/cnpj/issues
Keywords: cnpj,receita-federal,dados-abertos,brasil,empresas,estabelecimentos,data-processing,duckdb,parquet
Classifier: Development Status :: 4 - Beta
Classifier: Intended Audience :: Developers
Classifier: Intended Audience :: Financial and Insurance Industry
Classifier: Intended Audience :: Science/Research
Classifier: Operating System :: OS Independent
Classifier: Programming Language :: Python :: 3
Classifier: Programming Language :: Python :: 3.9
Classifier: Programming Language :: Python :: 3.10
Classifier: Programming Language :: Python :: 3.11
Classifier: Programming Language :: Python :: 3.12
Classifier: Topic :: Office/Business :: Financial
Classifier: Topic :: Scientific/Engineering :: Information Analysis
Classifier: Topic :: Software Development :: Libraries :: Python Modules
Requires-Python: >=3.9
License-File: LICENSE
Requires-Dist: beautifulsoup4>=4.12.0
Requires-Dist: duckdb>=0.10.0
Requires-Dist: python-dotenv>=1.0.0
Requires-Dist: aiohttp[speedups]>=3.9.5
Requires-Dist: aiofiles>=23.2.0
Requires-Dist: rich>=13.9.0
Requires-Dist: pyarrow>=19.0.0
Requires-Dist: matplotlib>=3.8.0
Requires-Dist: polars>=0.20.0
Requires-Dist: seaborn>=0.13.0
Requires-Dist: requests>=2.31.0
Requires-Dist: psutil>=5.9.8
Requires-Dist: pydantic>=2.0.0
Provides-Extra: dev
Requires-Dist: pytest>=7.0.0; extra == "dev"
Requires-Dist: pytest-asyncio>=0.21.0; extra == "dev"
Requires-Dist: pytest-cov>=4.0.0; extra == "dev"
Requires-Dist: black>=23.0.0; extra == "dev"
Requires-Dist: flake8>=6.0.0; extra == "dev"
Requires-Dist: mypy>=1.0.0; extra == "dev"
Requires-Dist: build>=0.10.0; extra == "dev"
Requires-Dist: twine>=4.0.0; extra == "dev"
Dynamic: license-file
